sas_lexer-1.0.0b2.dist-info/METADATA
sas_lexer-1.0.0b2.dist-info/WHEEL
sas_lexer-1.0.0b2.dist-info/licenses/LICENSE
sas_lexer/token.py
sas_lexer/error.py
sas_lexer/__init__.py
sas_lexer/token_channel.py
sas_lexer/error_kind.py
sas_lexer/token_type.py
sas_lexer/lexer.py
sas_lexer/py.typed
sas_lexer/_sas_lexer_rust.pyi
sas_lexer/_sas_lexer_rust.cpython-310-darwin.so
sas_lexer-1.0.0b2.dist-info/RECORD
