Metadata-Version: 2.4
Name: sas-lexer
Version: 1.0.0b2
Classifier: Development Status :: 4 - Beta
Classifier: Intended Audience :: Developers
Classifier: License :: OSI Approved :: GNU Affero General Public License v3 or later (AGPLv3+)
Classifier: Operating System :: MacOS
Classifier: Operating System :: Microsoft :: Windows
Classifier: Operating System :: POSIX :: Linux
Classifier: Programming Language :: Python :: 3
Classifier: Programming Language :: Python :: Implementation :: CPython
Classifier: Programming Language :: Rust
Classifier: Topic :: Software Development :: Compilers
Classifier: Topic :: Software Development :: Libraries :: Python Modules
Classifier: Topic :: Software Development :: Libraries
Classifier: Typing :: Typed
Requires-Dist: msgspec >=0.18.0
License-File: LICENSE
Summary: Ultra fast correct context-aware "parsing" SAS code lexer
Keywords: sas,lexer,parser
Author: Mike Perlov <mishamsk@gmail.com>
Author-email: Mike Perlov <mishamsk@gmail.com>
License: AGPL-3.0-or-later
Requires-Python: >=3.10, <3.13
Project-URL: homepage, https://github.com/mishamsk/sas-lexer
Project-URL: repository, https://github.com/mishamsk/sas-lexer
Project-URL: Issues, https://github.com/mishamsk/sas-lexer/issues
